python_combiner/__init__.py
python_combiner/__main__.py
python_combiner/cli.py
python_combiner/compiler.py
python_combiner/errors.py
python_combiner/exporthelper.py
python_combiner/graph.py
python_combiner/options.py
python_combiner/processedmodule.py
python_combiner/transformers.py
python_combiner/plugin/__init__.py
python_combiner/plugin/constants.py
python_combiner/plugin/minifier.py
python_combiner/plugin/plugin.py
python_combiner/plugin/prelude.py
python_combiner/plugin/simplify_if.py
python_combiner-0.3.0.dist-info/LICENSE
python_combiner-0.3.0.dist-info/METADATA
python_combiner-0.3.0.dist-info/WHEEL
python_combiner-0.3.0.dist-info/entry_points.txt
python_combiner-0.3.0.dist-info/top_level.txt
python_combiner-0.3.0.dist-info/RECORD
