Metadata-Version: 2.2
Name: python-combiner
Version: 0.3.0
Summary: Smoosh Python modules into one big one.
Author-email: zabackary <137591653+zabackary@users.noreply.github.com>
License: MIT
Project-URL: Homepage, https://github.com/zabackary/python-combiner
Project-URL: Issues, https://github.com/zabackary/python-combiner/issues
Classifier: Programming Language :: Python :: 3
Classifier: Operating System :: OS Independent
Requires-Python: >=3.12
License-File: LICENSE
Provides-Extra: minifier
Requires-Dist: python-minifier; extra == "minifier"
